README.md
setup.cfg
setup.py
BuyProxiesAPI.egg-info/PKG-INFO
BuyProxiesAPI.egg-info/SOURCES.txt
BuyProxiesAPI.egg-info/dependency_links.txt
BuyProxiesAPI.egg-info/requires.txt
BuyProxiesAPI.egg-info/top_level.txt
buyproxies_api/__init__.py
buyproxies_api/buyproxies_api.py
buyproxies_api/errors.py