Metadata-Version: 2.1
Name: BuyProxiesAPI
Version: 0.22
Summary: BuyProxies.org simple API Wrapper
Home-page: https://github.com/Druidmaciek/BuyProxies.org-API-Wrapper
Author: Maciej Janowski
Author-email: maciekjanowski@icloud.com
License: UNKNOWN
Download-URL: https://github.com/Druidmaciek/BuyProxies.org-API-Wrapper/archive/0.22.tar.gz
Project-URL: Bug Reports, https://github.com/Druidmaciek/BuyProxies.org-API-Wrapper/issues
Project-URL: Funding, https://paypal.me/druidmaciek
Project-URL: Source, https://github.com/Druidmaciek/BuyProxies.org-API-Wrapper
Keywords: web proxies development scraping buyproxies.org
Platform: UNKNOWN
Classifier: Development Status :: 3 - Alpha
Classifier: Intended Audience :: Developers
Classifier: Programming Language :: Python :: 3.6
Classifier: Programming Language :: Python :: 3.7
Requires-Python: >=3.6
